MANIFEST.in
README.rst
setup.py
flimfret/__init__.py
flimfret/analysis.py
flimfret.egg-info/PKG-INFO
flimfret.egg-info/SOURCES.txt
flimfret.egg-info/dependency_links.txt
flimfret.egg-info/not-zip-safe
flimfret.egg-info/requires.txt
flimfret.egg-info/top_level.txt