Metadata-Version: 1.1
Name: flimfret
Version: 0.3
Summary: Pipeline for FLIM FRET analysis
Home-page: http://github.com/casalex/flimfret
Author: Alex Casella
Author-email: alexmcasella@gmail.com
License: MIT
Platform: UNKNOWN
Classifier: Development Status :: 3 - Alpha
Classifier: Programming Language :: Python :: 2.7
